moosetash/__init__.py
moosetash/context.py
moosetash/exceptions.py
moosetash/handlers.py
moosetash/py.typed
moosetash/render.py
moosetash/tokenizer.py
moosetash/types.py
moosetash-1.0.1.dist-info/LICENSE
moosetash-1.0.1.dist-info/METADATA
moosetash-1.0.1.dist-info/WHEEL
moosetash-1.0.1.dist-info/entry_points.txt
moosetash-1.0.1.dist-info/RECORD
