Metadata-Version: 2.1
Name: moosetash
Version: 1.0.1
Summary: Mustache template renderer
Home-page: https://github.com/michaelrccurtis/moosetash
Keywords: mustache,template,text
Author: Michael Curtis
Author-email: michaelrccurtis@gmail.com
Requires-Python: >=3.8,<4.0
Classifier: Development Status :: 3 - Alpha
Classifier: Programming Language :: Python :: 3
Classifier: Programming Language :: Python :: 3.8
Classifier: Programming Language :: Python :: 3.9
Classifier: Programming Language :: Python :: 3.10
Classifier: Programming Language :: Python :: 3.11
Classifier: Topic :: Text Processing :: Markup
Classifier: Typing :: Typed
Project-URL: Repository, https://github.com/michaelrccurtis/moosetash
